Metadata-Version: 2.1
Name: chemistry-adapters
Version: 0.0.2
Summary: UNKNOWN
Home-page: https://www.github.com/Sulstice/ChemistryAdapters
Author: Suliman Sharif
Author-email: sharifsuliman1@gmail.com
License: MIT
Keywords: smiles molecules chemistry
Platform: UNKNOWN
Classifier: Development Status :: 4 - Beta
Classifier: Natural Language :: English
Classifier: License :: OSI Approved :: MIT License
Classifier: Intended Audience :: Developers
Classifier: Programming Language :: Python :: 3
Classifier: Programming Language :: Python :: 3.3
Classifier: Programming Language :: Python :: 3.4
Classifier: Programming Language :: Python :: 3.5
Classifier: Programming Language :: Python :: 3.6
Classifier: Programming Language :: Python :: 3.7
